[
  {
    "type": "binary_expr",
    "named": true,
    "fields": {
      "lhs": {
        "multiple": false,
        "required": true,
        "types": [
          {
            "type": "binary_expr",
            "named": true
          },
          {
            "type": "boolean",
            "named": true
          },
          {
            "type": "fn_call",
            "named": true
          },
          {
            "type": "identifier",
            "named": true
          },
          {
            "type": "number",
            "named": true
          },
          {
            "type": "prefix_expr",
            "named": true
          },
          {
            "type": "string",
            "named": true
          }
        ]
      },
      "operator": {
        "multiple": false,
        "required": true,
        "types": [
          {
            "type": "binary_operator",
            "named": true
          }
        ]
      },
      "rhs": {
        "multiple": false,
        "required": true,
        "types": [
          {
            "type": "binary_expr",
            "named": true
          },
          {
            "type": "boolean",
            "named": true
          },
          {
            "type": "fn_call",
            "named": true
          },
          {
            "type": "identifier",
            "named": true
          },
          {
            "type": "number",
            "named": true
          },
          {
            "type": "prefix_expr",
            "named": true
          },
          {
            "type": "string",
            "named": true
          }
        ]
      }
    }
  },
  {
    "type": "body_item",
    "named": true,
    "fields": {},
    "children": {
      "multiple": false,
      "required": true,
      "types": [
        {
          "type": "expr_stmt",
          "named": true
        },
        {
          "type": "return_stmt",
          "named": true
        },
        {
          "type": "variable_declaration",
          "named": true
        }
      ]
    }
  },
  {
    "type": "boolean",
    "named": true,
    "fields": {}
  },
  {
    "type": "expr_stmt",
    "named": true,
    "fields": {},
    "children": {
      "multiple": false,
      "required": true,
      "types": [
        {
          "type": "binary_expr",
          "named": true
        },
        {
          "type": "boolean",
          "named": true
        },
        {
          "type": "fn_call",
          "named": true
        },
        {
          "type": "identifier",
          "named": true
        },
        {
          "type": "number",
          "named": true
        },
        {
          "type": "prefix_expr",
          "named": true
        },
        {
          "type": "string",
          "named": true
        }
      ]
    }
  },
  {
    "type": "fn_call",
    "named": true,
    "fields": {
      "labeledArg": {
        "multiple": true,
        "required": false,
        "types": [
          {
            "type": "=",
            "named": false
          },
          {
            "type": "binary_expr",
            "named": true
          },
          {
            "type": "boolean",
            "named": true
          },
          {
            "type": "fn_call",
            "named": true
          },
          {
            "type": "identifier",
            "named": true
          },
          {
            "type": "number",
            "named": true
          },
          {
            "type": "prefix_expr",
            "named": true
          },
          {
            "type": "string",
            "named": true
          }
        ]
      },
      "unlabeledFirstArg": {
        "multiple": false,
        "required": false,
        "types": [
          {
            "type": "binary_expr",
            "named": true
          },
          {
            "type": "boolean",
            "named": true
          },
          {
            "type": "fn_call",
            "named": true
          },
          {
            "type": "identifier",
            "named": true
          },
          {
            "type": "number",
            "named": true
          },
          {
            "type": "prefix_expr",
            "named": true
          },
          {
            "type": "string",
            "named": true
          }
        ]
      }
    },
    "children": {
      "multiple": false,
      "required": true,
      "types": [
        {
          "type": "identifier",
          "named": true
        }
      ]
    }
  },
  {
    "type": "fn_definition",
    "named": true,
    "fields": {},
    "children": {
      "multiple": true,
      "required": true,
      "types": [
        {
          "type": "body_item",
          "named": true
        },
        {
          "type": "identifier",
          "named": true
        }
      ]
    }
  },
  {
    "type": "kcl_program",
    "named": true,
    "root": true,
    "fields": {},
    "children": {
      "multiple": true,
      "required": false,
      "types": [
        {
          "type": "body_item",
          "named": true
        }
      ]
    }
  },
  {
    "type": "non_fn_definition",
    "named": true,
    "fields": {},
    "children": {
      "multiple": true,
      "required": true,
      "types": [
        {
          "type": "binary_expr",
          "named": true
        },
        {
          "type": "boolean",
          "named": true
        },
        {
          "type": "fn_call",
          "named": true
        },
        {
          "type": "identifier",
          "named": true
        },
        {
          "type": "number",
          "named": true
        },
        {
          "type": "prefix_expr",
          "named": true
        },
        {
          "type": "string",
          "named": true
        }
      ]
    }
  },
  {
    "type": "prefix_expr",
    "named": true,
    "fields": {
      "operand": {
        "multiple": false,
        "required": true,
        "types": [
          {
            "type": "binary_expr",
            "named": true
          },
          {
            "type": "boolean",
            "named": true
          },
          {
            "type": "fn_call",
            "named": true
          },
          {
            "type": "identifier",
            "named": true
          },
          {
            "type": "number",
            "named": true
          },
          {
            "type": "prefix_expr",
            "named": true
          },
          {
            "type": "string",
            "named": true
          }
        ]
      },
      "operator": {
        "multiple": false,
        "required": true,
        "types": [
          {
            "type": "prefix_operator",
            "named": true
          }
        ]
      }
    }
  },
  {
    "type": "prefix_operator",
    "named": true,
    "fields": {}
  },
  {
    "type": "return_stmt",
    "named": true,
    "fields": {},
    "children": {
      "multiple": false,
      "required": true,
      "types": [
        {
          "type": "binary_expr",
          "named": true
        },
        {
          "type": "boolean",
          "named": true
        },
        {
          "type": "fn_call",
          "named": true
        },
        {
          "type": "identifier",
          "named": true
        },
        {
          "type": "number",
          "named": true
        },
        {
          "type": "prefix_expr",
          "named": true
        },
        {
          "type": "string",
          "named": true
        }
      ]
    }
  },
  {
    "type": "string",
    "named": true,
    "fields": {},
    "children": {
      "multiple": true,
      "required": false,
      "types": [
        {
          "type": "escape_sequence",
          "named": true
        }
      ]
    }
  },
  {
    "type": "variable_declaration",
    "named": true,
    "fields": {},
    "children": {
      "multiple": false,
      "required": true,
      "types": [
        {
          "type": "fn_definition",
          "named": true
        },
        {
          "type": "non_fn_definition",
          "named": true
        }
      ]
    }
  },
  {
    "type": "!",
    "named": false
  },
  {
    "type": "\"",
    "named": false
  },
  {
    "type": "(",
    "named": false
  },
  {
    "type": ")",
    "named": false
  },
  {
    "type": ",",
    "named": false
  },
  {
    "type": "-",
    "named": false
  },
  {
    "type": "=",
    "named": false
  },
  {
    "type": "binary_operator",
    "named": true
  },
  {
    "type": "escape_sequence",
    "named": true
  },
  {
    "type": "false",
    "named": false
  },
  {
    "type": "fn",
    "named": false
  },
  {
    "type": "identifier",
    "named": true
  },
  {
    "type": "number",
    "named": true
  },
  {
    "type": "return",
    "named": false
  },
  {
    "type": "true",
    "named": false
  },
  {
    "type": "{",
    "named": false
  },
  {
    "type": "}",
    "named": false
  }
]